README.md
setup.cfg
setup.py
SynChron.egg-info/PKG-INFO
SynChron.egg-info/SOURCES.txt
SynChron.egg-info/dependency_links.txt
SynChron.egg-info/requires.txt
SynChron.egg-info/top_level.txt
synchron/__init__.py
synchron/utils.py
synchron/newswidget/__init__.py
synchron/newswidget/newswidget.py
synchron/quotewidget/__init__.py
synchron/quotewidget/quotes.py
synchron/redditwidget/__init__.py
synchron/redditwidget/redditwidget.py
synchron/rsswidget/__init__.py
synchron/rsswidget/rsswidget.py
synchron/twitterwidget/__init__.py
synchron/twitterwidget/twitterwidget.py
synchron/udemywidget/__init__.py
synchron/udemywidget/udemywidget.py