Metadata-Version: 1.0
Name: SynChron
Version: 1.2.3
Summary: SynChron
Home-page: https://github.com/sequencecentral/SynChron.git
Author: Steve Ayers, Ph.D.
Author-email: steve@sequenccecentral.com
License: MIT
Platform: UNKNOWN
